LICENSE
MANIFEST.in
README.md
requirements.txt
setup.cfg
setup.py
test_requirements.txt
cic_contracts/__init__.py
cic_contracts/accounts_index.py
cic_contracts/base.py
cic_contracts/erc20.py
cic_contracts/names.py
cic_contracts/registry.py
cic_contracts/search.py
cic_contracts/writer.py
cic_contracts.egg-info/PKG-INFO
cic_contracts.egg-info/SOURCES.txt
cic_contracts.egg-info/dependency_links.txt
cic_contracts.egg-info/requires.txt
cic_contracts.egg-info/top_level.txt
cic_contracts/data/AccountsIndex.interface
cic_contracts/data/AccountsIndex.json
cic_contracts/data/AccountsIndexMutable.interface
cic_contracts/data/AccountsIndexMutable.json
cic_contracts/data/Burner.interface
cic_contracts/data/Burner.json
cic_contracts/data/Capped.interface
cic_contracts/data/Capped.json
cic_contracts/data/Chrono.interface
cic_contracts/data/Chrono.json
cic_contracts/data/Declarator.interface
cic_contracts/data/Declarator.json
cic_contracts/data/Digest.interface
cic_contracts/data/Digest.json
cic_contracts/data/ERC165.interface
cic_contracts/data/ERC165.json
cic_contracts/data/ERC173.interface
cic_contracts/data/ERC173.json
cic_contracts/data/ERC20.interface
cic_contracts/data/ERC20.json
cic_contracts/data/ERC5007.interface
cic_contracts/data/ERC5007.json
cic_contracts/data/ERC5192.interface
cic_contracts/data/ERC5192.json
cic_contracts/data/ERC5679Ext20.interface
cic_contracts/data/ERC5679Ext20.json
cic_contracts/data/ERC5679Ext721.interface
cic_contracts/data/ERC5679Ext721.json
cic_contracts/data/ERC721.interface
cic_contracts/data/ERC721.json
cic_contracts/data/ERC721Enumerable.interface
cic_contracts/data/ERC721Enumerable.json
cic_contracts/data/ERC721Metadata.interface
cic_contracts/data/ERC721Metadata.json
cic_contracts/data/ERC721Receiver.interface
cic_contracts/data/ERC721Receiver.json
cic_contracts/data/Expire.interface
cic_contracts/data/Expire.json
cic_contracts/data/Faucet.interface
cic_contracts/data/Faucet.json
cic_contracts/data/Locator.interface
cic_contracts/data/Locator.json
cic_contracts/data/Minter.interface
cic_contracts/data/Minter.json
cic_contracts/data/Msg.interface
cic_contracts/data/Msg.json
cic_contracts/data/MultiHash.interface
