Metadata-Version: 2.1
Name: cic-contracts
Version: 0.3.8
Summary: CIC network smart contract interfaces
Home-page: https://gitlab.com/cicnet/cic-contracts
Author: Louis Holbrook
Author-email: dev@holbrook.no
License: GPL3
Keywords: dlt,blockchain,cryptocurrency,ethereum
Classifier: Programming Language :: Python :: 3
Classifier: Operating System :: OS Independent
Classifier: Development Status :: 3 - Alpha
Classifier: Topic :: Software Development :: Libraries
Classifier: Environment :: Console
Classifier: Intended Audience :: Developers
Classifier: License :: OSI Approved :: GNU General Public License v3 or later (GPLv3+)
Classifier: Topic :: Internet
Requires-Python: <3.11,>=3.8
License-File: LICENSE
